{
    "finance": {
        "result": [
            {
                "count": 20,
                "quotes": [
                    {
                        "language": "en-US",
                        "region": "US",
                        "quoteType": "EQUITY",
                        "triggerable": true,
                        "quoteSourceName": "Delayed Quote",
                        "regularMarketTime": 1603396802,
                        "regularMarketChange": 0.45999908,
                        "marketState": "PREPRE",
                        "shortName": "Gilead Sciences, Inc.",
                        "exchange": "NMS",
                        "regularMarketPrice": 60.67,
                        "market": "us_market",
                        "sourceInterval": 15,
                        "exchangeTimezoneName": "America/New_York",
                        "exchangeTimezoneShortName": "EDT",
                        "gmtOffSetMilliseconds": -14400000,
                        "esgPopulated": false,
                        "tradeable": false,
                        "regularMarketChangePercent": 0.7639912,
                        "regularMarketPreviousClose": 60.21,
                        "fullExchangeName": "NasdaqGS",
                        "longName": "Gilead Sciences, Inc.",
                        "exchangeDataDelayedBy": 0,
                        "priceHint": 2,
                        "symbol": "GILD"
                    },
                    {
                        "language": "en-US",
                        "region": "US",
                        "quoteType": "EQUITY",
                        "triggerable": true,
                        "quoteSourceName": "Delayed Quote",
                        "regularMarketTime": 1603396802,
                        "regularMarketChange": 0.40000153,
                        "marketState": "PREPRE",
                        "shortName": "Intel Corporation",
                        "exchange": "NMS",
                        "regularMarketPrice": 53.9,
                        "market": "us_market",
                        "sourceInterval": 15,
                        "exchangeTimezoneName": "America/New_York",
                        "exchangeTimezoneShortName": "EDT",
                        "gmtOffSetMilliseconds": -14400000,
                        "esgPopulated": false,
                        "tradeable": false,
                        "regularMarketChangePercent": 0.7476664,
                        "regularMarketPreviousClose": 53.5,
                        "fullExchangeName": "NasdaqGS",
                        "longName": "Intel Corporation",
                        "exchangeDataDelayedBy": 0,
                        "priceHint": 2,
                        "symbol": "INTC"
                    },
                    {
                        "language": "en-US",
                        "region": "US",
                        "quoteType": "EQUITY",
                        "triggerable": true,
                        "quoteSourceName": "Delayed Quote",
                        "regularMarketTime": 1603396802,
                        "regularMarketChange": 26.180023,
                        "marketState": "PREPRE",
                        "shortName": "Snowflake Inc.",
                        "exchange": "NYQ",
                        "regularMarketPrice": 296.79,
                        "market": "us_market",
                        "sourceInterval": 15,
                        "exchangeTimezoneName": "America/New_York",
                        "exchangeTimezoneShortName": "EDT",
                        "gmtOffSetMilliseconds": -14400000,
                        "esgPopulated": false,
                        "tradeable": false,
                        "regularMarketChangePercent": 9.674449,
                        "regularMarketPreviousClose": 270.61,
                        "fullExchangeName": "NYSE",
                        "longName": "Snowflake Inc.",
                        "exchangeDataDelayedBy": 0,
                        "priceHint": 2,
                        "symbol": "SNOW"
                    },
                    {
                        "language": "en-US",
                        "region": "US",
                        "quoteType": "EQUITY",
                        "triggerable": true,
                        "quoteSourceName": "Delayed Quote",
                        "regularMarketTime": 1603396802,
                        "regularMarketChange": 1.1500092,
                        "marketState": "PREPRE",
                        "shortName": "Johnson & Johnson",
                        "exchange": "NYQ",
                        "regularMarketPrice": 145.08,
                        "market": "us_market",
                        "sourceInterval": 15,
                        "exchangeTimezoneName": "America/New_York",
                        "exchangeTimezoneShortName": "EDT",
                        "gmtOffSetMilliseconds": -14400000,
                        "esgPopulated": false,
                        "tradeable": false,
                        "regularMarketChangePercent": 0.7990059,
                        "regularMarketPreviousClose": 143.93,
                        "fullExchangeName": "NYSE",
                        "longName": "Johnson & Johnson",
                        "exchangeDataDelayedBy": 0,
                        "priceHint": 2,
                        "symbol": "JNJ"
                    },
                    {
                        "language": "en-US",
                        "region": "US",
                        "quoteType": "EQUITY",
                        "triggerable": false,
                        "quoteSourceName": "Delayed Quote",
                        "regularMarketTime": 1603432817,
                        "regularMarketChange": 1.0999985,
                        "marketState": "REGULAR",
                        "shortName": "HSBC HOLDINGS",
                        "exchange": "HKG",
                        "regularMarketPrice": 32.35,
                        "market": "hk_market",
                        "sourceInterval": 15,
                        "exchangeTimezoneName": "Asia/Hong_Kong",
                        "exchangeTimezoneShortName": "HKT",
                        "gmtOffSetMilliseconds": 28800000,
                        "esgPopulated": false,
                        "tradeable": false,
                        "regularMarketChangePercent": 3.5199952,
                        "regularMarketPreviousClose": 31.25,
                        "fullExchangeName": "HKSE",
                        "longName": "HSBC Holdings plc",
                        "exchangeDataDelayedBy": 0,
                        "priceHint": 3,
                        "symbol": "0005.HK"
                    },
                    {
                        "language": "en-US",
                        "region": "US",
                        "quoteType": "EQUITY",
                        "triggerable": true,
                        "quoteSourceName": "Delayed Quote",
                        "regularMarketTime": 1603396802,
                        "regularMarketChange": 2.2200012,
                        "marketState": "PREPRE",
                        "shortName": "Delta Air Lines, Inc.",
                        "exchange": "NYQ",
                        "regularMarketPrice": 33.72,
                        "market": "us_market",
                        "sourceInterval": 15,
                        "exchangeTimezoneName": "America/New_York",
                        "exchangeTimezoneShortName": "EDT",
                        "gmtOffSetMilliseconds": -14400000,
                        "esgPopulated": false,
                        "tradeable": false,
                        "regularMarketChangePercent": 7.0476227,
                        "regularMarketPreviousClose": 31.5,
                        "fullExchangeName": "NYSE",
                        "longName": "Delta Air Lines, Inc.",
                        "exchangeDataDelayedBy": 0,
                        "priceHint": 2,
                        "symbol": "DAL"
                    },
                    {
                        "language": "en-US",
                        "region": "US",
                        "quoteType": "EQUITY",
                        "triggerable": true,
                        "quoteSourceName": "Delayed Quote",
                        "regularMarketTime": 1603396801,
                        "regularMarketChange": 0.39999962,
                        "marketState": "PREPRE",
                        "shortName": "General Electric Company",
                        "exchange": "NYQ",
                        "regularMarketPrice": 7.72,
                        "market": "us_market",
                        "sourceInterval": 15,
                        "exchangeTimezoneName": "America/New_York",
                        "exchangeTimezoneShortName": "EDT",
                        "gmtOffSetMilliseconds": -14400000,
                        "esgPopulated": false,
                        "tradeable": false,
                        "regularMarketChangePercent": 5.4644756,
                        "regularMarketPreviousClose": 7.32,
                        "fullExchangeName": "NYSE",
                        "longName": "General Electric Company",
                        "exchangeDataDelayedBy": 0,
                        "priceHint": 2,
                        "symbol": "GE"
                    },
                    {
                        "language": "en-US",
                        "region": "US",
                        "quoteType": "EQUITY",
                        "triggerable": true,
                        "quoteSourceName": "Delayed Quote",
                        "regularMarketTime": 1603396999,
                        "regularMarketChange": 2.539999,
                        "marketState": "PREPRE",
                        "shortName": "Gap, Inc. (The)",
                        "exchange": "NYQ",
                        "regularMarketPrice": 21.15,
                        "market": "us_market",
                        "sourceInterval": 15,
                        "exchangeTimezoneName": "America/New_York",
                        "exchangeTimezoneShortName": "EDT",
                        "gmtOffSetMilliseconds": -14400000,
                        "esgPopulated": false,
                        "tradeable": false,
                        "regularMarketChangePercent": 13.648569,
                        "regularMarketPreviousClose": 18.61,
                        "fullExchangeName": "NYSE",
                        "longName": "The Gap, Inc.",
                        "exchangeDataDelayedBy": 0,
                        "priceHint": 2,
                        "symbol": "GPS"
                    },
                    {
                        "language": "en-US",
                        "region": "US",
                        "quoteType": "EQUITY",
                        "triggerable": true,
                        "quoteSourceName": "Delayed Quote",
                        "regularMarketTime": 1603396801,
                        "regularMarketChange": 2.4699936,
                        "marketState": "PREPRE",
                        "shortName": "Moderna, Inc.",
                        "exchange": "NMS",
                        "regularMarketPrice": 70.84,
                        "market": "us_market",
                        "sourceInterval": 15,
                        "exchangeTimezoneName": "America/New_York",
                        "exchangeTimezoneShortName": "EDT",
                        "gmtOffSetMilliseconds": -14400000,
                        "esgPopulated": false,
                        "tradeable": false,
                        "regularMarketChangePercent": 3.612686,
                        "regularMarketPreviousClose": 68.37,
                        "fullExchangeName": "NasdaqGS",
                        "longName": "Moderna, Inc.",
                        "exchangeDataDelayedBy": 0,
                        "priceHint": 2,
                        "symbol": "MRNA"
                    },
                    {
                        "language": "en-US",
                        "region": "US",
                        "quoteType": "EQUITY",
                        "triggerable": true,
                        "quoteSourceName": "Delayed Quote",
                        "regularMarketTime": 1603396801,
                        "regularMarketChange": 9.959999,
                        "marketState": "PREPRE",
                        "shortName": "Unity Software Inc.",
                        "exchange": "NYQ",
                        "regularMarketPrice": 100.96,
                        "market": "us_market",
                        "sourceInterval": 15,
                        "exchangeTimezoneName": "America/New_York",
                        "exchangeTimezoneShortName": "EDT",
                        "gmtOffSetMilliseconds": -14400000,
                        "esgPopulated": false,
                        "tradeable": false,
                        "regularMarketChangePercent": 10.945054,
                        "regularMarketPreviousClose": 91,
                        "fullExchangeName": "NYSE",
                        "longName": "Unity Software Inc.",
                        "exchangeDataDelayedBy": 0,
                        "priceHint": 2,
                        "symbol": "U"
                    },
                    {
                        "language": "en-US",
                        "region": "US",
                        "quoteType": "EQUITY",
                        "triggerable": true,
                        "quoteSourceName": "Delayed Quote",
                        "regularMarketTime": 1603396801,
                        "regularMarketChange": -0.07999992,
                        "marketState": "PREPRE",
                        "shortName": "Cassava Sciences, Inc.",
                        "exchange": "NMS",
                        "regularMarketPrice": 8.83,
                        "market": "us_market",
                        "sourceInterval": 15,
                        "exchangeTimezoneName": "America/New_York",
                        "exchangeTimezoneShortName": "EDT",
                        "gmtOffSetMilliseconds": -14400000,
                        "esgPopulated": false,
                        "tradeable": false,
                        "regularMarketChangePercent": -0.8978668,
                        "regularMarketPreviousClose": 8.91,
                        "fullExchangeName": "NasdaqGS",
                        "longName": "Cassava Sciences, Inc.",
                        "exchangeDataDelayedBy": 0,
                        "priceHint": 2,
                        "symbol": "SAVA"
                    },
                    {
                        "language": "en-US",
                        "region": "US",
                        "quoteType": "EQUITY",
                        "triggerable": true,
                        "quoteSourceName": "Free Realtime Quote",
                        "regularMarketTime": 1603433726,
                        "regularMarketChange": -36.400024,
                        "marketState": "REGULAR",
                        "shortName": "SBI CARDS & PAYMEN",
                        "exchange": "NSI",
                        "regularMarketPrice": 815.5,
                        "market": "in_market",
                        "sourceInterval": 15,
                        "exchangeTimezoneName": "Asia/Kolkata",
                        "exchangeTimezoneShortName": "IST",
                        "gmtOffSetMilliseconds": 19800000,
                        "esgPopulated": false,
                        "tradeable": false,
                        "regularMarketChangePercent": -4.2728047,
                        "regularMarketPreviousClose": 851.9,
                        "fullExchangeName": "NSE",
                        "longName": "SBI Cards and Payment Services Limited",
                        "exchangeDataDelayedBy": 15,
                        "priceHint": 2,
                        "symbol": "SBICARD.NS"
                    },
                    {
                        "language": "en-US",
                        "region": "US",
                        "quoteType": "EQUITY",
                        "triggerable": true,
                        "quoteSourceName": "Delayed Quote",
                        "regularMarketTime": 1603397014,
                        "regularMarketChange": 0.36000013,
                        "marketState": "PREPRE",
                        "shortName": "Ford Motor Company",
                        "exchange": "NYQ",
                        "regularMarketPrice": 8.21,
                        "market": "us_market",
                        "sourceInterval": 15,
                        "exchangeTimezoneName": "America/New_York",
                        "exchangeTimezoneShortName": "EDT",
                        "gmtOffSetMilliseconds": -14400000,
                        "esgPopulated": false,
                        "tradeable": false,
                        "regularMarketChangePercent": 4.585989,
                        "regularMarketPreviousClose": 7.85,
                        "fullExchangeName": "NYSE",
                        "longName": "Ford Motor Company",
                        "exchangeDataDelayedBy": 0,
                        "priceHint": 2,
                        "symbol": "F"
                    },
                    {
                        "language": "en-US",
                        "region": "US",
                        "quoteType": "EQUITY",
                        "triggerable": true,
                        "quoteSourceName": "Delayed Quote",
                        "regularMarketTime": 1603396801,
                        "regularMarketChange": 1.1100001,
                        "marketState": "PREPRE",
                        "shortName": "Sabre Corporation",
                        "exchange": "NMS",
                        "regularMarketPrice": 7.76,
                        "market": "us_market",
                        "sourceInterval": 15,
                        "exchangeTimezoneName": "America/New_York",
                        "exchangeTimezoneShortName": "EDT",
                        "gmtOffSetMilliseconds": -14400000,
                        "esgPopulated": false,
                        "tradeable": false,
                        "regularMarketChangePercent": 16.69173,
                        "regularMarketPreviousClose": 6.65,
                        "fullExchangeName": "NasdaqGS",
                        "longName": "Sabre Corporation",
                        "exchangeDataDelayedBy": 0,
                        "priceHint": 2,
                        "symbol": "SABR"
                    },
                    {
                        "language": "en-US",
                        "region": "US",
                        "quoteType": "EQUITY",
                        "triggerable": true,
                        "quoteSourceName": "Delayed Quote",
                        "regularMarketTime": 1603396802,
                        "regularMarketChange": 1.43,
                        "marketState": "PREPRE",
                        "shortName": "Ever-Glory International Group,",
                        "exchange": "NGM",
                        "regularMarketPrice": 2.6,
                        "market": "us_market",
                        "sourceInterval": 15,
                        "exchangeTimezoneName": "America/New_York",
                        "exchangeTimezoneShortName": "EDT",
                        "gmtOffSetMilliseconds": -14400000,
                        "esgPopulated": false,
                        "tradeable": false,
                        "regularMarketChangePercent": 122.22222,
                        "regularMarketPreviousClose": 1.17,
                        "fullExchangeName": "NasdaqGM",
                        "longName": "Ever-Glory International Group, Inc.",
                        "exchangeDataDelayedBy": 0,
                        "priceHint": 4,
                        "symbol": "EVK"
                    },
                    {
                        "language": "en-US",
                        "region": "US",
                        "quoteType": "EQUITY",
                        "triggerable": true,
                        "quoteSourceName": "Delayed Quote",
                        "regularMarketTime": 1603396802,
                        "regularMarketChange": 1.7099991,
                        "marketState": "PREPRE",
                        "shortName": "Celsius Holdings, Inc.",
                        "exchange": "NMS",
                        "regularMarketPrice": 22.99,
                        "market": "us_market",
                        "sourceInterval": 15,
                        "exchangeTimezoneName": "America/New_York",
                        "exchangeTimezoneShortName": "EDT",
                        "gmtOffSetMilliseconds": -14400000,
                        "esgPopulated": false,
                        "tradeable": false,
                        "regularMarketChangePercent": 8.035709,
                        "regularMarketPreviousClose": 21.28,
                        "fullExchangeName": "NasdaqGS",
                        "longName": "Celsius Holdings, Inc.",
                        "exchangeDataDelayedBy": 0,
                        "priceHint": 2,
                        "symbol": "CELH"
                    },
                    {
                        "language": "en-US",
                        "region": "US",
                        "quoteType": "EQUITY",
                        "triggerable": true,
                        "quoteSourceName": "Delayed Quote",
                        "regularMarketTime": 1603396801,
                        "regularMarketChange": 0.055000305,
                        "marketState": "PREPRE",
                        "shortName": "Limelight Networks, Inc.",
                        "exchange": "NMS",
                        "regularMarketPrice": 6.175,
                        "market": "us_market",
                        "sourceInterval": 15,
                        "exchangeTimezoneName": "America/New_York",
                        "exchangeTimezoneShortName": "EDT",
                        "gmtOffSetMilliseconds": -14400000,
                        "esgPopulated": false,
                        "tradeable": false,
                        "regularMarketChangePercent": 0.8986978,
                        "regularMarketPreviousClose": 6.12,
                        "fullExchangeName": "NasdaqGS",
                        "longName": "Limelight Networks, Inc.",
                        "exchangeDataDelayedBy": 0,
                        "priceHint": 2,
                        "symbol": "LLNW"
                    },
                    {
                        "language": "en-US",
                        "region": "US",
                        "quoteType": "EQUITY",
                        "triggerable": true,
                        "quoteSourceName": "Delayed Quote",
                        "regularMarketTime": 1603396802,
                        "regularMarketChange": 0.3199997,
                        "marketState": "PREPRE",
                        "shortName": "eHealth, Inc.",
                        "exchange": "NMS",
                        "regularMarketPrice": 82.02,
                        "market": "us_market",
                        "sourceInterval": 15,
                        "exchangeTimezoneName": "America/New_York",
                        "exchangeTimezoneShortName": "EDT",
                        "gmtOffSetMilliseconds": -14400000,
                        "esgPopulated": false,
                        "tradeable": false,
                        "regularMarketChangePercent": 0.39167652,
                        "regularMarketPreviousClose": 81.7,
                        "fullExchangeName": "NasdaqGS",
                        "longName": "eHealth, Inc.",
                        "exchangeDataDelayedBy": 0,
                        "priceHint": 2,
                        "symbol": "EHTH"
                    },
                    {
                        "language": "en-US",
                        "region": "US",
                        "quoteType": "EQUITY",
                        "triggerable": true,
                        "quoteSourceName": "Delayed Quote",
                        "regularMarketTime": 1603396802,
                        "regularMarketChange": 2.7300005,
                        "marketState": "PREPRE",
                        "shortName": "Sequential Brands Group, Inc.",
                        "exchange": "NMS",
                        "regularMarketPrice": 8.43,
                        "market": "us_market",
                        "sourceInterval": 15,
                        "exchangeTimezoneName": "America/New_York",
                        "exchangeTimezoneShortName": "EDT",
                        "gmtOffSetMilliseconds": -14400000,
                        "esgPopulated": false,
                        "tradeable": false,
                        "regularMarketChangePercent": 47.894745,
                        "regularMarketPreviousClose": 5.7,
                        "fullExchangeName": "NasdaqGS",
                        "longName": "Sequential Brands Group, Inc.",
                        "exchangeDataDelayedBy": 0,
                        "priceHint": 2,
                        "symbol": "SQBG"
                    },
                    {
                        "language": "en-US",
                        "region": "US",
                        "quoteType": "EQUITY",
                        "triggerable": true,
                        "quoteSourceName": "Delayed Quote",
                        "regularMarketTime": 1603396801,
                        "regularMarketChange": -0.059999943,
                        "marketState": "PREPRE",
                        "shortName": "Socket Mobile, Inc.",
                        "exchange": "NMS",
                        "regularMarketPrice": 1.46,
                        "market": "us_market",
                        "sourceInterval": 15,
                        "exchangeTimezoneName": "America/New_York",
                        "exchangeTimezoneShortName": "EDT",
                        "gmtOffSetMilliseconds": -14400000,
                        "esgPopulated": false,
                        "tradeable": false,
                        "regularMarketChangePercent": -3.9473646,
                        "regularMarketPreviousClose": 1.52,
                        "fullExchangeName": "NasdaqGS",
                        "longName": "Socket Mobile, Inc.",
                        "exchangeDataDelayedBy": 0,
                        "priceHint": 4,
                        "symbol": "SCKT"
                    }
                ],
                "jobTimestamp": 1603429716606,
                "startInterval": 202010230400
            }
        ],
        "error": null
    }
}